increment_counter/__init__.py
increment_counter/app.py
increment_counter/static/asset-manifest.json
increment_counter/static/favicon.ico
increment_counter/static/index.html
increment_counter/static/logo192.png
increment_counter/static/logo512.png
increment_counter/static/manifest.json
increment_counter/static/robots.txt
increment_counter/static/css/main.cb3e59d9.css
increment_counter/static/css/main.cb3e59d9.css.map
increment_counter/static/js/453.4ccd4c5d.chunk.js
increment_counter/static/js/453.4ccd4c5d.chunk.js.map
increment_counter/static/js/main.9e735d15.js
increment_counter/static/js/main.9e735d15.js.LICENSE.txt
increment_counter/static/js/main.9e735d15.js.map
increment_counter/templates/index.html
increment_counter-0.5.dist-info/METADATA
increment_counter-0.5.dist-info/WHEEL
increment_counter-0.5.dist-info/entry_points.txt
increment_counter-0.5.dist-info/top_level.txt
increment_counter-0.5.dist-info/RECORD
