Metadata-Version: 2.1
Name: increment-counter
Version: 0.5
Classifier: Programming Language :: Python :: 3
Classifier: Framework :: Flask
Classifier: Operating System :: OS Independent
Requires-Dist: flask
Requires-Dist: flask-cors
